jflat/__about__.py
jflat/__init__.py
jflat/flatten.py
jflat/unflatten.py
jflat/tests/__init__.py
jflat/tests/test_flatten.py
jflat/tests/test_unflatten.py
jflat-0.1.4.dist-info/METADATA
jflat-0.1.4.dist-info/WHEEL
jflat-0.1.4.dist-info/licenses/LICENSE
jflat-0.1.4.dist-info/RECORD
