Metadata-Version: 2.4
Name: jflat
Version: 0.1.4
Summary: A humble library for flattening Python dictionaries according to their JSON-path
Project-URL: Homepage, https://github.com/merschformann/jflat
Project-URL: Repository, https://github.com/merschformann/jflat
Author-email: Marius Merschformann <merschformann@proton.me>
Maintainer-email: Marius Merschformann <merschformann@proton.me>
License: MIT License
License-File: LICENSE
Keywords: dict,dictionary,flatten,json,json-path,nested
Classifier: License :: OSI Approved :: Apache Software License
Classifier: Operating System :: OS Independent
Classifier: Programming Language :: Python :: 3
Classifier: Programming Language :: Python :: 3.9
Classifier: Programming Language :: Python :: 3.10
Classifier: Programming Language :: Python :: 3.11
Classifier: Programming Language :: Python :: 3.12
Classifier: Programming Language :: Python :: 3.13
Requires-Python: >=3.9
Provides-Extra: dev
Requires-Dist: ruff; extra == 'dev'
